smolqwery/__init__.py
smolqwery/_utils.py
smolqwery/apps.py
smolqwery/bigqwery.py
smolqwery/config.py
smolqwery/extractor.py
smolqwery/management/commands/smolqwery_extract.py
smolqwery/management/commands/smolqwery_make_migrations.py
smolqwery/management/commands/smolqwery_print_extract.py
smolqwery/swallow.py
smolqwery-0.1.3.dist-info/METADATA
smolqwery-0.1.3.dist-info/WHEEL
smolqwery-0.1.3.dist-info/RECORD
