Metadata-Version: 2.1
Name: smolqwery
Version: 0.1.3
Summary: A Django-oriented tool to make analytics exports to BigQuery
Home-page: https://github.com/Xowap/smolqwery
License: WTFPL
Author: Rémy Sanchez
Author-email: remy.sanchez@hyperthese.net
Requires-Python: >=3.8
Classifier: License :: Other/Proprietary License
Classifier: Programming Language :: Python :: 3
Classifier: Programming Language :: Python :: 3.8
Classifier: Programming Language :: Python :: 3.9
Classifier: Programming Language :: Python :: 3.10
Classifier: Programming Language :: Python :: 3.11
Classifier: Programming Language :: Python :: 3.12
Requires-Dist: black (>=20)
Requires-Dist: google-cloud-bigquery (>=2)
Requires-Dist: python-dateutil (>=2)
Requires-Dist: rich (>=11)
Project-URL: Repository, https://github.com/Xowap/smolqwery
